README.rst
setup.py
cnfhash/__init__.py
cnfhash/__main__.py
cnfhash/hashing.py
cnfhash/run.py
cnfhash.egg-info/PKG-INFO
cnfhash.egg-info/SOURCES.txt
cnfhash.egg-info/dependency_links.txt
cnfhash.egg-info/entry_points.txt
cnfhash.egg-info/top_level.txt