Metadata-Version: 1.1
Name: cnfhash
Version: 2.1.2
Summary: CNF hashing implemented in python3
Home-page: http://lukas-prokop.at/proj/cnf-hash/
Author: Lukas Prokop
Author-email: admin@lukas-prokop.at
License: Public Domain
Platform: any
Classifier: Development Status :: 6 - Mature
Classifier: Environment :: Console
Classifier: Intended Audience :: Developers
Classifier: Intended Audience :: Education
Classifier: Intended Audience :: Science/Research
Classifier: License :: Public Domain
Classifier: Natural Language :: English
Classifier: Operating System :: OS Independent
Classifier: Programming Language :: Python :: 3 :: Only
Classifier: Programming Language :: Python :: 3.6
Classifier: Topic :: Scientific/Engineering
